contextal/__init__.py
contextal/__main__.py
contextal/cmd.py
contextal/cmd_config.py
contextal/cmd_download.py
contextal/cmd_query.py
contextal/cmd_scenario.py
contextal/cmd_work.py
contextal/config.py
contextal/ctx_scan.py
contextal/misc.py
contextal/platform.py
contextal-1.0.1.dist-info/METADATA
contextal-1.0.1.dist-info/WHEEL
contextal-1.0.1.dist-info/entry_points.txt
contextal-1.0.1.dist-info/licenses/LICENSE.txt
contextal-1.0.1.dist-info/RECORD
