Metadata-Version: 2.3
Name: contextal
Version: 1.0.1
Summary: Contextal Platform management library and tools.
Project-URL: Homepage, https://contextal.com/
License-File: LICENSE.txt
Classifier: License :: OSI Approved :: MIT License
Classifier: Operating System :: OS Independent
Classifier: Programming Language :: Python :: 3
Requires-Python: >=3.10
Requires-Dist: platformdirs
Requires-Dist: requests
Requires-Dist: tomlkit
